envipyarclib/__init__.py
envipyarclib/gptoolbox.py
envipyarclib/metaclass.py
envipyarclib/system.py
envipyarclib/gptool/__init__.py
envipyarclib/gptool/help.py
envipyarclib/gptool/parameter/__init__.py
envipyarclib/gptool/parameter/builder.py
envipyarclib/gptool/parameter/template.py
envipyarclib/gptool/parameter/templates/__init__.py
envipyarclib/gptool/parameter/templates/basic.py
envipyarclib/gptool/parameter/templates/basicarray.py
envipyarclib/gptool/parameter/templates/bool.py
envipyarclib/gptool/parameter/templates/boolarray.py
envipyarclib/gptool/parameter/templates/boolean.py
envipyarclib/gptool/parameter/templates/byte.py
envipyarclib/gptool/parameter/templates/bytearray.py
envipyarclib/gptool/parameter/templates/double.py
envipyarclib/gptool/parameter/templates/doublearray.py
envipyarclib/gptool/parameter/templates/enviuri.py
envipyarclib/gptool/parameter/templates/enviuriarray.py
envipyarclib/gptool/parameter/templates/envivirtualizableuri.py
envipyarclib/gptool/parameter/templates/envivirtualizableuriarray.py
envipyarclib/gptool/parameter/templates/float.py
envipyarclib/gptool/parameter/templates/floatarray.py
envipyarclib/gptool/parameter/templates/int.py
envipyarclib/gptool/parameter/templates/intarray.py
envipyarclib/gptool/parameter/templates/long.py
envipyarclib/gptool/parameter/templates/long64.py
envipyarclib/gptool/parameter/templates/long64array.py
envipyarclib/gptool/parameter/templates/longarray.py
envipyarclib/gptool/parameter/templates/string.py
envipyarclib/gptool/parameter/templates/stringarray.py
envipyarclib/gptool/parameter/templates/uint.py
envipyarclib/gptool/parameter/templates/uintarray.py
envipyarclib/gptool/parameter/templates/ulong.py
envipyarclib/gptool/parameter/templates/ulong64.py
envipyarclib/gptool/parameter/templates/ulong64array.py
envipyarclib/gptool/parameter/templates/ulongarray.py
envipyarclib/test/__init__.py
envipyarclib/test/config.py
envipyarclib-1.0.8.dist-info/DESCRIPTION.rst
envipyarclib-1.0.8.dist-info/METADATA
envipyarclib-1.0.8.dist-info/RECORD
envipyarclib-1.0.8.dist-info/WHEEL
envipyarclib-1.0.8.dist-info/metadata.json
envipyarclib-1.0.8.dist-info/top_level.txt
