Metadata-Version: 2.0
Name: envipyarclib
Version: 1.0.8
Summary: ENVI Py Client Utilities for ArcGIS
Home-page: https://github.com/envi-idl/envipyarclib
Author: Harris Geospatial Solutions, Inc.
Author-email: UNKNOWN
License: MIT
Platform: UNKNOWN
